pyrdv/__init__.py
pyrdv/bar.py
pyrdv/dashboard.py
pyrdv/gantt.py
pyrdv/line.py
pyrdv/point.py
pyrdv-1.0.1.dist-info/LICENSE
pyrdv-1.0.1.dist-info/METADATA
pyrdv-1.0.1.dist-info/WHEEL
pyrdv-1.0.1.dist-info/top_level.txt
pyrdv-1.0.1.dist-info/RECORD
