Metadata-Version: 2.1
Name: pyrdv
Version: 1.0.1
Summary: reshape data visualization library in py language 
Home-page: http://www.reshapedata.com
Author: Reshapedata
Author-email: hulilei@takewiki.com.cn
License: Apache License
Keywords: reshapedata,rdv,pyrdv
Platform: UNKNOWN
Requires-Python: >=3.6
Requires-Dist: requests
